praisonaiwp/__init__.py
praisonaiwp/__main__.py
praisonaiwp/__version__.py
praisonaiwp/ai/__init__.py
praisonaiwp/ai/duplicate_detector.py
praisonaiwp/ai/integration.py
praisonaiwp/ai/smart_agent.py
praisonaiwp/ai/tools/__init__.py
praisonaiwp/ai/tools/wordpress_tools.py
praisonaiwp/ai/utils/__init__.py
praisonaiwp/ai/utils/cost_tracker.py
praisonaiwp/ai/utils/rate_limiter.py
praisonaiwp/ai/utils/retry.py
praisonaiwp/ai/utils/validators.py
praisonaiwp/cli/__init__.py
praisonaiwp/cli/main.py
praisonaiwp/cli/commands/__init__.py
praisonaiwp/cli/commands/ability.py
praisonaiwp/cli/commands/admin.py
praisonaiwp/cli/commands/ai_analyzer.py
praisonaiwp/cli/commands/ai_bulk.py
praisonaiwp/cli/commands/ai_chatbot.py
praisonaiwp/cli/commands/ai_commands.py
praisonaiwp/cli/commands/ai_curator.py
praisonaiwp/cli/commands/ai_image.py
praisonaiwp/cli/commands/ai_moderator.py
praisonaiwp/cli/commands/ai_optimizer.py
praisonaiwp/cli/commands/ai_researcher.py
praisonaiwp/cli/commands/ai_scheduler.py
praisonaiwp/cli/commands/ai_seo.py
praisonaiwp/cli/commands/ai_summarizer.py
praisonaiwp/cli/commands/ai_translator.py
praisonaiwp/cli/commands/ai_workflow.py
praisonaiwp/cli/commands/backup.py
praisonaiwp/cli/commands/block.py
praisonaiwp/cli/commands/cache.py
praisonaiwp/cli/commands/cap.py
praisonaiwp/cli/commands/category.py
praisonaiwp/cli/commands/cli.py
praisonaiwp/cli/commands/comment.py
praisonaiwp/cli/commands/config.py
praisonaiwp/cli/commands/core.py
praisonaiwp/cli/commands/create.py
praisonaiwp/cli/commands/cron.py
praisonaiwp/cli/commands/db.py
praisonaiwp/cli/commands/dist-archive.py
praisonaiwp/cli/commands/duplicate.py
praisonaiwp/cli/commands/embed.py
praisonaiwp/cli/commands/eval-file.py
praisonaiwp/cli/commands/eval.py
praisonaiwp/cli/commands/find.py
praisonaiwp/cli/commands/find_wordpress.py
praisonaiwp/cli/commands/help.py
praisonaiwp/cli/commands/i18n.py
praisonaiwp/cli/commands/import_export.py
praisonaiwp/cli/commands/init.py
praisonaiwp-1.10.0.dist-info/METADATA
praisonaiwp-1.10.0.dist-info/WHEEL
praisonaiwp-1.10.0.dist-info/entry_points.txt
praisonaiwp-1.10.0.dist-info/licenses/LICENSE
praisonaiwp-1.10.0.dist-info/RECORD
