Metadata-Version: 2.4
Name: praisonaiwp
Version: 1.10.0
Summary: AI-powered WordPress content management with PraisonAI integration and production-ready features
Project-URL: Homepage, https://github.com/MervinPraison/praisonaiwp
Project-URL: Documentation, https://praisonaiwp.readthedocs.io
Project-URL: Repository, https://github.com/MervinPraison/praisonaiwp
Project-URL: Issues, https://github.com/MervinPraison/praisonaiwp/issues
Author-email: Praison <your.email@example.com>
License: MIT
License-File: LICENSE
Keywords: automation,cms,content-management,wordpress,wp-cli
Classifier: Development Status :: 4 - Beta
Classifier: Intended Audience :: Developers
Classifier: License :: OSI Approved :: MIT License
Classifier: Programming Language :: Python :: 3
Classifier: Programming Language :: Python :: 3.8
Classifier: Programming Language :: Python :: 3.9
Classifier: Programming Language :: Python :: 3.10
Classifier: Programming Language :: Python :: 3.11
Classifier: Programming Language :: Python :: 3.12
Classifier: Topic :: Software Development :: Libraries :: Python Modules
Requires-Python: >=3.8.1
Requires-Dist: click>=8.1.0
Requires-Dist: mysql-connector-python>=8.0.33
Requires-Dist: paramiko>=3.0.0
Requires-Dist: python-dotenv>=1.0.0
Requires-Dist: pyyaml>=6.0
Requires-Dist: requests>=2.31.0
Requires-Dist: rich>=13.0.0
Requires-Dist: tqdm>=4.65.0
Provides-Extra: ai
Requires-Dist: praisonai[llm]>=3.9.21; (python_version >= '3.10') and extra == 'ai'
Provides-Extra: all
Requires-Dist: black>=23.0.0; extra == 'all'
Requires-Dist: flake8>=6.0.0; extra == 'all'
Requires-Dist: mcp[cli]>=1.2.0; (python_version >= '3.10') and extra == 'all'
Requires-Dist: mypy>=1.0.0; extra == 'all'
Requires-Dist: praisonai[llm]>=3.9.21; (python_version >= '3.10') and extra == 'all'
Requires-Dist: pytest-cov>=4.0.0; extra == 'all'
Requires-Dist: pytest-mock>=3.10.0; extra == 'all'
Requires-Dist: pytest>=7.0.0; extra == 'all'
Requires-Dist: ruff>=0.1.0; extra == 'all'
Provides-Extra: dev
Requires-Dist: black>=23.0.0; extra == 'dev'
Requires-Dist: flake8>=6.0.0; extra == 'dev'
Requires-Dist: mypy>=1.0.0; extra == 'dev'
Requires-Dist: pytest-cov>=4.0.0; extra == 'dev'
Requires-Dist: pytest-mock>=3.10.0; extra == 'dev'
Requires-Dist: pytest>=7.0.0; extra == 'dev'
Requires-Dist: ruff>=0.1.0; extra == 'dev'
Provides-Extra: mcp
Requires-Dist: mcp[cli]>=1.2.0; (python_version >= '3.10') and extra == 'mcp'
